pixegami_hello/__init__.py
pixegami_hello/main.py
test_pkhan_12345-0.5.0.dist-info/METADATA
test_pkhan_12345-0.5.0.dist-info/WHEEL
test_pkhan_12345-0.5.0.dist-info/entry_points.txt
test_pkhan_12345-0.5.0.dist-info/top_level.txt
test_pkhan_12345-0.5.0.dist-info/RECORD
