Metadata-Version: 2.1
Name: test-pkhan-12345
Version: 0.5.0
Requires-Dist: numpy >=1.13.3
Requires-Dist: scipy >=0.19.1
